RatingCF/ISCF.py
RatingCF/SCF.py
RatingCF/__init__.py
RatingCF-0.1.2.dist-info/LICENSE.txt
RatingCF-0.1.2.dist-info/METADATA
RatingCF-0.1.2.dist-info/WHEEL
RatingCF-0.1.2.dist-info/top_level.txt
RatingCF-0.1.2.dist-info/RECORD
